CHANGELOG.txt
LICENCE.txt
MANIFEST.in
README.txt
__init__.py
req.txt
setup.py
vocode/__init__.py
vocode/helpers.py
vocode/streaming/__init__.py
vocode/streaming/constants.py
vocode/streaming/hosted_streaming_conversation.py
vocode/streaming/streaming_conversation.py
vocode/streaming/agent/__init__.py
vocode/streaming/agent/anthropic_agent.py
vocode/streaming/agent/base_agent.py
vocode/streaming/agent/bot_sentiment_analyser.py
vocode/streaming/agent/chat_gpt_agent.py
vocode/streaming/agent/echo_agent.py
vocode/streaming/agent/factory.py
vocode/streaming/agent/gpt4all_agent.py
vocode/streaming/agent/information_retrieval_agent.py
vocode/streaming/agent/llm_agent.py
vocode/streaming/agent/restful_user_implemented_agent.py
vocode/streaming/agent/utils.py
vocode/streaming/client_backend/__init__.py
vocode/streaming/client_backend/conversation.py
vocode/streaming/input_device/__init__.py
vocode/streaming/input_device/base_input_device.py
vocode/streaming/input_device/file_input_device.py
vocode/streaming/input_device/microphone_input.py
vocode/streaming/models/__init__.py
vocode/streaming/models/agent.py
vocode/streaming/models/audio_encoding.py
vocode/streaming/models/client_backend.py
vocode/streaming/models/events.py
vocode/streaming/models/message.py
vocode/streaming/models/model.py
vocode/streaming/models/synthesizer.py
vocode/streaming/models/telephony.py
vocode/streaming/models/transcriber.py
vocode/streaming/models/transcript.py
vocode/streaming/models/websocket.py
vocode/streaming/output_device/__init__.py
vocode/streaming/output_device/base_output_device.py
vocode/streaming/output_device/blocking_speaker_output.py
vocode/streaming/output_device/file_output_device.py
vocode/streaming/output_device/speaker_output.py
vocode/streaming/output_device/twilio_output_device.py
vocode/streaming/output_device/websocket_output_device.py
vocode/streaming/synthesizer/__init__.py
vocode/streaming/synthesizer/azure_synthesizer.py
vocodesaaslabs.egg-info/PKG-INFO
vocodesaaslabs.egg-info/SOURCES.txt
vocodesaaslabs.egg-info/dependency_links.txt
vocodesaaslabs.egg-info/requires.txt
vocodesaaslabs.egg-info/top_level.txt