Metadata-Version: 2.1
Name: vocodesaaslabs
Version: 0.0.7
Summary: SaaS Labs version of Vocode
Home-page: 
Author: Ajeya Krishna
Author-email: ajeya@saaslabs.co
License: MIT
Keywords: voice
Classifier: Development Status :: 5 - Production/Stable
Classifier: Intended Audience :: Education
Classifier: Operating System :: MacOS
Classifier: License :: OSI Approved :: MIT License
Classifier: Programming Language :: Python :: 3
License-File: LICENCE.txt
Requires-Dist: pydub<0.26.0,>=0.25.1
Requires-Dist: nltk<4.0.0,>=3.8.1
Requires-Dist: langchain<0.0.150,>=0.0.149
Requires-Dist: openai<0.28.0,>=0.27.4
Requires-Dist: sounddevice<0.5.0,>=0.4.6
Requires-Dist: azure-cognitiveservices-speech<2.0.0,>=1.27.0
Requires-Dist: websockets<12.0.0,>=11.0.2
Requires-Dist: requests<3.0.0,>=2.28.2
Requires-Dist: uvicorn<0.22.0,>=0.21.1
Requires-Dist: fastapi<0.96.0,>=0.95.1
Requires-Dist: jinja2<4.0.0,>=3.1.2
Requires-Dist: python-multipart<0.0.7,>=0.0.6
Requires-Dist: six<2.0.0,>=1.16.0
Requires-Dist: opentelemetry-sdk<2.0.0,>=1.17.0
Requires-Dist: janus<2.0.0,>=1.0.0
Requires-Dist: scipy<2.0.0,>=1.10.1
Requires-Dist: anthropic<0.3.0,>=0.2.9
Requires-Dist: elevenlabs<0.3.0,>=0.2.6
Requires-Dist: google-cloud-texttospeech<3.0.0,>=2.14.1
Requires-Dist: gtts<3.0.0,>=2.3.1
Requires-Dist: google-cloud-speech<3.0.0,>=2.19.0
Requires-Dist: redis<5.0.0,>=4.5.4
Requires-Dist: twilio<9.0.0,>=8.1.0
